phonon/__init__.py
phonon/client.py
phonon/event.py
phonon/exceptions.py
phonon/fields.py
phonon/lock.py
phonon/model.py
phonon/nodelist.py
phonon/reference.py
phonon/registry.py
phonon/connections/__init__.py
phonon-3.1.dist-info/DESCRIPTION.rst
phonon-3.1.dist-info/METADATA
phonon-3.1.dist-info/RECORD
phonon-3.1.dist-info/WHEEL
phonon-3.1.dist-info/metadata.json
phonon-3.1.dist-info/top_level.txt
test/__init__.py
test/field_test.py
test/model_test.py
test/nodelist_test.py
test/process_test.py
test/reference_test.py
test/registry_test.py
test/test_client.py
