Metadata-Version: 1.1
Name: phonon
Version: 3.1
Summary: Provides easy, fault tolerant, distributed references with redis as a backend.
Home-page: http://www.github.com/akellehe/phonon
Author: Andrew Kelleher
Author-email: andrew@scale-rabbit.com
License: UNKNOWN
Keywords: distributed reference references aggregation pipeline big data online algorithm
Platform: UNKNOWN
Classifier: Intended Audience :: Developers
Classifier: Intended Audience :: System Administrators
Classifier: Development Status :: 4 - Beta
